shard_llm/__init__.py
shard_llm/collator.py
shard_llm/converter.py
shard_llm/dataset.py
shard_llm/generator.py
shard_llm/logo.png
shard_llm/README.md
shard_llm/setup.py
shard_llm/tuner.py
shard_llm-1.0.6.dist-info/LICENSE
shard_llm-1.0.6.dist-info/METADATA
shard_llm-1.0.6.dist-info/WHEEL
shard_llm-1.0.6.dist-info/RECORD
