Metadata-Version: 2.3
Name: shard-llm
Version: 1.0.6
Summary: Shard is an open-source LLM tuning package for Python, which can turn any causal LLM into a specific character.
Author: matjsz
Author-email: matjsz42@gmail.com
Requires-Python: >=3.12
Classifier: Programming Language :: Python :: 3
Classifier: Programming Language :: Python :: 3.12
Classifier: Programming Language :: Python :: 3.13
Requires-Dist: bitsandbytes (>=0.45.4,<0.46.0)
Requires-Dist: datasets (>=3.4.1,<4.0.0)
Requires-Dist: peft (>=0.15.0,<0.16.0)
Requires-Dist: transformers (>=4.50.1,<5.0.0)
